bondzai.media_handler-0.0.19-py3.10-nspkg.pth
bondzai/media_handler/__init__.py
bondzai/media_handler/audio.py
bondzai/media_handler/base.py
bondzai/media_handler/data_packager.py
bondzai/media_handler/generic.py
bondzai/media_handler/image.py
bondzai/media_handler/registry.py
bondzai/media_handler/video.py
tests/__init__.py
tests/test_audio.py
tests/test_data_packager.py
tests/test_generic.py
tests/test_image.py
tests/test_video.py
bondzai.media_handler-0.0.19.dist-info/METADATA
bondzai.media_handler-0.0.19.dist-info/NOTICE
bondzai.media_handler-0.0.19.dist-info/WHEEL
bondzai.media_handler-0.0.19.dist-info/namespace_packages.txt
bondzai.media_handler-0.0.19.dist-info/top_level.txt
bondzai.media_handler-0.0.19.dist-info/zip-safe
bondzai.media_handler-0.0.19.dist-info/RECORD
