Metadata-Version: 2.1
Name: bondzai.media-handler
Version: 0.0.19
Summary: Bondzai Media Handler
Home-page: UNKNOWN
Author: Bondzai
License: Apache License 2.0
Keywords: davinsy,bondzai,media
Platform: UNKNOWN
Classifier: Programming Language :: Python :: 3
Classifier: License :: OSI Approved :: Apache Software License
Classifier: Operating System :: OS Independent
License-File: NOTICE
Requires-Dist: pytest (==7.2.0)
Requires-Dist: PyYAML (==6.0.0)
Requires-Dist: numpy (==2.0.2)
Requires-Dist: soundfile (==0.12.1)
Requires-Dist: audio-metadata (==0.11.1)
Requires-Dist: imageio (==2.30.0)
Requires-Dist: imageio-ffmpeg (==0.4.8)
